pixi/__init__.py
pixi/__main__.py
pixi/chatbot.py
pixi/chatting.py
pixi/client.py
pixi/commands.py
pixi/database.py
pixi/utils.py
pixi/addon/__init__.py
pixi/addon/addon_manager.py
pixi/agents/__init__.py
pixi/agents/base.py
pixi/agents/retrievalagent.py
pixi/apis/__init__.py
pixi/apis/api.py
pixi/apis/tenor.py
pixi/apis/wikimedia.py
pixi/caching/__init__.py
pixi/caching/audiocache.py
pixi/caching/base.py
pixi/caching/embedding.py
pixi/caching/imagecache.py
pixi/config/__init__.py
pixi/config/dataset.py
pixi/config/features.py
pixi/config/filter.py
pixi/config/mediawiki.py
pixi/config/openai.py
pixi/enums/__init__.py
pixi/enums/messages.py
pixi/reflection/__init__.py
pixi/reflection/discord.py
pixi/reflection/telegram.py
pixi/reflection/message/__init__.py
pixi/reflection/message/discord.py
pixi/reflection/message/telegram.py
pixi/resources/examples.txt
pixi/resources/persona.json
pixi/resources/system.md
pixi/typing/__init__.py
pixi_bot-1.3.1.dist-info/licenses/LICENSE
pixi_bot-1.3.1.dist-info/METADATA
pixi_bot-1.3.1.dist-info/WHEEL
pixi_bot-1.3.1.dist-info/entry_points.txt
pixi_bot-1.3.1.dist-info/top_level.txt
pixi_bot-1.3.1.dist-info/RECORD
