Metadata-Version: 2.4
Name: pixi-bot
Version: 1.3.1
Summary: A modular and multiplatform AI chatbot
Requires-Python: >=3.10
License-File: LICENSE
Requires-Dist: argparse>=1.0
Requires-Dist: dotenv>=0.9
Requires-Dist: numpy>=2.0
Requires-Dist: openai>=2.0
Requires-Dist: zstandard>=0.25
Provides-Extra: media
Requires-Dist: av>=16.0; extra == "media"
Provides-Extra: telegram
Requires-Dist: python-telegram-bot>=22.0; extra == "telegram"
Provides-Extra: discord
Requires-Dist: discord-py>=2.6; extra == "discord"
Dynamic: license-file
